{"Department of Energy": {"2017": {"agency": "Department of Energy", "year": "2017", "wd_ct": 67, "aw_ct": 1, "ids": ["227743_DE-SC0017246"], "AGROVOC": {"carbon_dioxide": 2, "membranes": 1, "fossil_fuels": 1, "society": 1, "combustion": 1, "pressure": 1, "mepiquat": 1, "heat": 1}, "REEGLE": {"carbon_dioxide": 3, "fossil_energy": 1, "biomass_combustion": 1}, "GEMET": {"carbon_dioxide": 3, "flue_gas": 2, "cost": 1, "fossil": 1, "energy": 1, "society": 1, "biomass": 1, "pressure": 1}, "EUSCIVOC": {"carbon_dioxide": 3, "fossil_energy": 1}, "EUVOC": {"greenhouse_gas": 3, "literature": 1, "chemical_process": 1}, "STW": {"greenhouse_gas_emissions": 3, "literature": 1, "costs": 1, "energy": 1, "process": 1}, "MeSH": {"Carbon_Dioxide": 1, "Fossil_Fuels": 1}, "textrank": {"pressure atm": 1, "post": 1}, "tfidf_keywords": {"temperature oc gas": 0, "society post combustion": 0, "society post": 0, "problem society post": 0, "oc gas co": 0, "oc gas": 0, "membrane amount carbon": 0, "fuel problem society": 0, "fossil fuel problem": 0, "cost membrane amount": 0}}, "2018": {"agency": "Department of Energy", "year": "2018", "wd_ct": 67, "aw_ct": 1, "ids": ["235508_DE-SC0017246"], "AGROVOC": {"carbon_dioxide": 2, "membranes": 1, "fossil_fuels": 1, "society": 1, "combustion": 1, "pressure": 1, "mepiquat": 1, "heat": 1}, "REEGLE": {"carbon_dioxide": 3, "fossil_energy": 1, "biomass_combustion": 1}, "GEMET": {"carbon_dioxide": 3, "flue_gas": 2, "cost": 1, "fossil": 1, "energy": 1, "society": 1, "biomass": 1, "pressure": 1}, "EUSCIVOC": {"carbon_dioxide": 3, "fossil_energy": 1}, "EUVOC": {"greenhouse_gas": 3, "literature": 1, "chemical_process": 1}, "STW": {"greenhouse_gas_emissions": 3, "literature": 1, "costs": 1, "energy": 1, "process": 1}, "MeSH": {"Carbon_Dioxide": 1, "Fossil_Fuels": 1}, "textrank": {"pressure atm": 1, "post": 1}, "tfidf_keywords": {"temperature oc gas": 0, "society post combustion": 0, "society post": 0, "problem society post": 0, "oc gas co": 0, "oc gas": 0, "membrane amount carbon": 0, "fuel problem society": 0, "fossil fuel problem": 0, "cost membrane amount": 0}}}, "National Science Foundation": {"2012": {"agency": "National Science Foundation", "year": "2012", "wd_ct": 384, "aw_ct": 1, "ids": ["1142594_1142594"], "AGROVOC": {"metrology": 7, "equipment": 5, "structures": 2, "measure": 2, "features": 2, "inspection": 2, "industry": 2, "manufacturing": 2, "methodology": 1, "down": 1, "demand": 1, "components": 1, "needs": 1, "deficiencies": 1, "mepiquat": 1, "ability": 1, "fenoprop": 1, "size": 1, "processes": 1, "production": 1, "quality_of_life": 1, "electronics": 1, "quality": 1, "measurement": 1}, "REEGLE": {"projects": 2, "inspections": 2, "industry": 2, "manufacturing": 2, "innovation": 1, "quality_of_life": 1, "crop_yields": 1}, "GEMET": {"metrology": 7, "equipment": 5, "research": 3, "sensor": 2, "industry": 2, "business": 1, "innovation": 1, "methodology": 1, "demand": 1, "quality_of_life": 1, "fluidics": 1, "electronics": 1, "quality_control": 1}, "EUVOC": {"literature": 3, "research_method": 1, "supply_and_demand": 1, "company_member": 1}, "STW": {"measurement": 4, "literature": 3, "labour": 3, "innovation": 1, "scientific_method": 1, "supply": 1, "demand": 1, "future": 1, "scientific_modelling": 1, "process": 1, "enterprise": 1, "production": 1, "quality_of_life": 1, "progress": 1, "quality": 1, "control": 1, "production_process": 1}, "MeSH": {"Small_Business": 1, "Quality_of_Life": 1, "Equipment_and_Supplies": 1, "Quality_Control": 1}, "textrank": {"phase": 4, "research": 3, "process": 2, "industry": 2, "advancement": 1, "feature": 1, "sidewall tool": 0, "project metrology sensor measurement": 0, "advance manufacturing quality": 0}, "tfidf_keywords": {"metrology": 7, "mems": 5, "sidewall": 3, "measurement": 3, "tool": 3, "aspect ratio": 3, "ratio microstructure": 0, "industry mems": 0, "feature sidewall": 0, "aspect ratio microstructure": 0}}, "2014": {"agency": "National Science Foundation", "year": "2014", "wd_ct": 289, "aw_ct": 1, "ids": ["1417032_1417032"], "AGROVOC": {"calibration": 6, "manufacturing": 5, "time": 4, "calcium_ammonium_nitrate": 3, "measure": 3, "production": 2, "metrology": 1, "plants": 1, "industry": 1, "scale": 1, "measurement": 1, "processes": 1, "inspection": 1, "state": 1, "dynamics": 1, "mepiquat": 1}, "REEGLE": {"manufacturing": 5, "technology_transfer": 1, "projects": 1, "uncertainty": 1, "industry": 1, "inspections": 1}, "GEMET": {"calibration": 6, "time": 4, "freedom": 3, "laser": 3, "calcium": 3, "ammonium": 3, "nitrate": 3, "market": 3, "metrology": 1, "business": 1, "technology_transfer": 1, "point": 1, "packaging": 1, "need": 1, "industry": 1, "technology": 1, "loss": 1, "equipment": 1, "state": 1, "art": 1}, "EUVOC": {"chemical_salt": 6, "apparatus_based_on_the_use_of_rays": 3, "literature": 2}, "STW": {"freedom": 3, "measurement": 3, "market": 3, "technology": 2, "literature": 2, "control": 1, "customers": 1, "risk": 1, "plants": 1, "production": 1, "machinery": 1, "robot": 1, "loss": 1, "lead_time": 1, "process": 1, "state": 1, "labour": 1}, "MeSH": {"Small_Business": 1, "Technology_Transfer": 1}, "textrank": {"precision": 3, "measurement": 2, "production": 2, "technology": 2, "manufacturer": 1, "laser interferometer calibration": 0, "time product": 0, "manufacturing measuring": 0, "chip market": 0}, "tfidf_keywords": {"calibration": 6, "chip": 4, "interferometer": 3, "freedom": 3, "precision": 3, "calibration time": 1, "axis": 1, "degree": 1, "interferometer market": 0, "degree freedom": 0}}}, "Department of Defense": {"2016": {"agency": "Department of Defense", "year": "2016", "wd_ct": 196, "aw_ct": 1, "ids": ["H161-003-0099_W81XWH-16-C-0165"], "AGROVOC": {"data": 4, "measurement": 2, "monitoring": 1, "world": 1, "economic_systems": 1, "quality": 1, "resources": 1, "bureaucracy": 1, "humans": 1, "approaches": 1, "time": 1, "analysis": 1, "knowledge": 1, "training": 1, "development": 1, "machine_learning": 1, "calcium_ammonium_nitrate": 1}, "REEGLE": {"monitoring": 1, "sustainable_livelihoods_approaches": 1, "international_development": 1, "program_evaluations": 1}, "GEMET": {"rate": 2, "monitoring": 1, "world": 1, "time": 1, "environment": 1, "approach": 1, "analysis": 1, "representation": 1, "model": 1, "training": 1, "well": 1, "calcium": 1, "ammonium": 1, "nitrate": 1}, "EUSCIVOC": {"machine_learning": 1}, "EUVOC": {"chemical_salt": 2, "administrative_formalities": 1, "two_wheeled_vehicle": 1}, "STW": {"data": 4, "measurement": 3, "health_care": 2, "world": 1, "quality": 1, "process": 1, "vehicle": 1, "environment": 1, "knowledge_representation": 1, "international": 1, "artificial_intelligence": 1}, "MeSH": {"United_States": 1, "Artificial_Intelligence": 1}, "textrank": {"algorithm": 3, "platform": 3, "value": 3, "care": 3, "patient": 3, "problem": 2, "healthcare": 2, "trump": 1, "datum": 0, "outcome": 0}, "tfidf_keywords": {"algorithm": 3, "value": 3, "care": 3, "cycle care": 0, "world economy struggle": 0, "value century healthcare": 0, "value century": 0, "trump relationship approach": 0, "trump relationship": 0, "transfer datum machine": 0}}, "2017": {"agency": "Department of Defense", "year": "2017", "wd_ct": 368, "aw_ct": 2, "ids": ["S163-002-0243_H92222-17-P-0023", "S172-001-0072_H92222-17-P-0077"], "AGROVOC": {"application": 3, "components": 2, "energy_sources": 1, "weight": 1, "flight": 1, "aircraft": 1, "wear": 1, "systems": 1, "time": 1, "requirements": 1, "calcium_ammonium_nitrate": 1, "ability": 1, "techniques": 1, "procedures": 1, "solutions": 1, "north_carolina": 1, "roots": 1, "communities": 1, "world": 1, "development": 1, "scale": 1}, "REEGLE": {"engines_for_renewables": 3, "technical_feasibility": 2, "energy": 1, "aircraft": 1, "carbon": 1, "international_development": 1, "trainers": 1}, "GEMET": {"well": 2, "coating": 2, "cost": 1, "energy": 1, "weight": 1, "aircraft": 1, "approach": 1, "carbon": 1, "time": 1, "family": 1, "calcium": 1, "ammonium": 1, "nitrate": 1, "world": 1, "business": 1}, "EUVOC": {"chemical_salt": 2, "armed_forces": 1, "gift": 1, "literature": 1}, "STW": {"costs": 1, "energy": 1, "greenhouse_gas_emissions": 1, "literature": 1, "world": 1, "international": 1, "labour": 1}, "MeSH": {"Weight": 1, "North_Carolina": 1}, "textrank": {"canine": 6, "special_operations_forces_abbr": 4, "application": 3, "engine": 3, "research_and_development_abbr": 3, "ncc": 2, "nccs": 1, "command": 1, "durability coating": 0, "failure": 0, "layer": 0, "design": 0, "team expert": 0, "subject_matter_experts_abbr feasibility": 0, "option": 0}, "tfidf_keywords": {"canine": 6, "special_operations_forces_abbr": 4, "team": 4, "bearing": 3, "durability": 3, "engine": 3, "research_and_development_abbr": 3, "ncc coating": 2, "ncc": 2, "coating": 2, "unmanned_aerial_vehicle_abbr": 2, "canine response": 2, "subject_matter_experts_abbr": 2, "component durability": 1, "use carbon nanocomposite": 0, "upt ncc coating": 0, "canine response inhibitor": 0, "team canine": 0, "response inhibitor": 0, "trainer handler instructor": 0}}, "2008": {"agency": "Department of Defense", "year": "2008", "wd_ct": 401, "aw_ct": 2, "ids": ["F073-139-0153_FA9302-08-M-0014", "N08A-028-0040_N00014-08-M-0289"], "AGROVOC": {"energy_sources": 9, "cells": 5, "water": 3, "analytes": 2, "site": 1, "mitigation": 1, "strategies": 1, "contamination": 1, "systems": 1, "analysis": 1, "portability": 1, "mass": 1, "results": 1, "energy": 1, "equipment": 1, "monitoring": 1, "electrodes": 1, "calcium_ammonium_nitrate": 1, "fenoprop": 1, "efficiency": 1, "management": 1, "microbiology": 1, "design": 1, "telemetry": 1}, "REEGLE": {"energy": 10, "fuel_cells": 4, "microbial_fuel_cells": 3, "marines": 3, "freshwater_availability": 2, "tradable_permits": 2, "water_resources": 1, "mitigation_strategies": 1, "accumulators": 1, "technical_feasibility": 1, "monitoring": 1, "energy_efficiency": 1}, "GEMET": {"energy": 10, "fuel": 8, "detection": 4, "density": 3, "freshwater": 2, "approach": 2, "well": 2, "cost": 2, "need": 1, "sensor": 1, "contamination": 1, "method": 1, "analysis": 1, "instrumentation": 1, "research": 1, "equipment": 1, "biological_monitoring": 1, "laboratory": 1, "calcium": 1, "ammonium": 1, "nitrate": 1, "management": 1, "microbiology": 1, "telemetry": 1, "field": 1, "trial": 1}, "EUSCIVOC": {"sustainable_energy": 1}, "EUVOC": {"chemical_salt": 2, "tool_industry": 1, "pollution": 1, "biology": 1, "designs_and_models": 1, "legal_hearing": 1}, "STW": {"energy": 10, "fuel": 8, "measurement": 3, "costs": 2, "measurement_technology": 1, "water": 1, "labour": 1, "laboratory": 1, "management": 1, "life_sciences": 1}, "MeSH": {"Bioelectric_Energy_Sources": 3, "Drinking_Water": 2, "Electric_Power_Supplies": 1, "Renewable_Energy": 1, "Environmental_Monitoring": 1}, "textrank": {"detection": 4, "phase": 3, "approach": 2, "sensor": 1, "trihalomethane measurement": 1, "performance power": 0, "fuel cell power": 0, "colonization electrode": 0}, "tfidf_keywords": {"power": 9, "fuel": 8, "sensor": 5, "detection": 4, "trihalomethane": 3, "sensor array": 3, "detection system": 3, "power density": 3, "drinking water": 2, "drinking": 2, "fuel cell": 2, "sensor array system": 1, "array system": 1, "analyte": 0, "power density fuel": 0, "density fuel cell": 0, "density fuel": 0, "fuel cell power": 0, "fuel cell colonization": 0, "cell colonization": 0}}, "2009": {"agency": "Department of Defense", "year": "2009", "wd_ct": 194, "aw_ct": 1, "ids": ["N091-014-0149_N68936-09-C-0084"], "AGROVOC": {"calcium_ammonium_nitrate": 3, "aircraft": 3, "energy": 2, "protection": 2, "materials": 1, "radar": 1, "development": 1, "radio": 1, "energy_sources": 1, "individuals": 1, "windows": 1, "optical_properties": 1}, "REEGLE": {"aircraft": 3, "energy": 2, "international_development": 1, "soil_erosion": 1}, "GEMET": {"laser": 4, "calcium": 3, "ammonium": 3, "nitrate": 3, "aircraft": 3, "detection": 2, "energy": 2, "exposure": 2, "radar": 1, "radio": 1, "weapon": 1, "history": 1, "cost": 1, "soil_erosion": 1}, "EUSCIVOC": {"radio_frequency": 1}, "EUVOC": {"chemical_salt": 6, "apparatus_based_on_the_use_of_rays": 4, "crew": 2, "waveband": 1, "military_equipment": 1, "armed_forces": 1}, "STW": {"energy": 2, "helicopter": 1, "international": 1, "armed_forces": 1, "business_history": 1, "costs": 1, "soil_erosion": 1}, "textrank": {"laser": 4, "united_protective_technologies_abbr": 3, "emi": 3, "aircraft": 3, "protection": 2, "energy": 2, "airframe": 1, "canopy window": 0}, "tfidf_keywords": {"laser": 4, "united_protective_technologies_abbr": 3, "canopy": 3, "emi": 3, "aircrew": 2, "airframe": 1, "windscreen laminate": 1, "source emi": 0, "year development battlefield": 0, "windscreen laminate erosion": 0}}, "2010": {"agency": "Department of Defense", "year": "2010", "wd_ct": 241, "aw_ct": 1, "ids": ["N08A-028-0040_N00014-10-C-0184"], "AGROVOC": {"energy_sources": 8, "engineering": 3, "systems": 3, "monitoring": 2, "approaches": 2, "electrodes": 2, "scale": 2, "fenoprop": 2, "cells": 1, "energy": 1, "equipment": 1, "microorganisms": 1, "calcium_ammonium_nitrate": 1, "levels": 1, "processes": 1, "experimentation": 1, "management": 1, "telemetry": 1, "needs": 1, "traffic": 1, "data": 1, "testing": 1, "collaboration": 1}, "REEGLE": {"energy": 9, "marines": 3, "monitoring": 2, "sustainable_livelihoods_approaches": 2, "microbial_fuel_cells": 1, "cost_effectiveness": 1}, "GEMET": {"energy": 9, "density": 3, "engineering": 3, "field": 3, "fuel": 2, "cost": 2, "sensor": 2, "equipment": 1, "biological_monitoring": 1, "calcium": 1, "ammonium": 1, "nitrate": 1, "laboratory": 1, "management": 1, "telemetry": 1, "traffic_monitoring": 1}, "EUSCIVOC": {"sustainable_energy": 1}, "EUVOC": {"technology": 3, "chemical_salt": 2, "communications_policy": 1, "management_techniques": 1}, "STW": {"energy": 9, "technology": 3, "fuel": 2, "costs": 2, "management": 2, "navy": 2, "laboratory": 1, "data": 1}, "MeSH": {"Bioelectric_Energy_Sources": 1, "Electric_Power_Supplies": 1, "Renewable_Energy": 1, "Environmental_Monitoring": 1, "Military_Personnel": 1}, "textrank": {"power": 8, "benthic_microbial_fuel_cells_abbr": 5, "engineering": 3, "phase": 3, "monitoring": 2, "sensor": 2, "navy": 2, "long": 2, "bmfc": 2, "colonization electrode": 0}, "tfidf_keywords": {"power": 8, "benthic_microbial_fuel_cells_abbr": 5, "power density": 3, "bmfc": 2, "colonization": 2, "power density benthic_microbial_fuel_cells_abbr": 1, "density benthic_microbial_fuel_cells_abbr": 1, "benthic_microbial_fuel_cells_abbr power": 0, "benthic_microbial_fuel_cells_abbr goal": 0, "engineering approach": 0}}, "2011": {"agency": "Department of Defense", "year": "2011", "wd_ct": 182, "aw_ct": 1, "ids": ["N102-142-1293_N68335-11-C-0023"], "AGROVOC": {"steel": 3, "calcium_ammonium_nitrate": 3, "processes": 2, "geometry": 2, "hardening": 2, "alloys": 1, "firmness": 1, "components": 1, "teeth": 1}, "REEGLE": {"carbon": 4}, "GEMET": {"carbon": 4, "steel": 3, "calcium": 3, "ammonium": 3, "nitrate": 3, "gas": 3, "region": 2, "material": 1, "chemical": 1, "deposition": 1}, "EUVOC": {"chemical_salt": 6, "mathematics": 2, "life_expectancy": 1}, "STW": {"greenhouse_gas_emissions": 4, "steel": 3, "process": 2, "region": 2, "mathematics": 2, "mortality": 1, "core": 1, "labour": 1, "machine_parts": 1, "navy": 1}, "textrank": {"carburization": 5, "carbon": 4, "steel": 3, "gear": 3, "gas": 3, "case": 2, "surface region": 1}, "tfidf_keywords": {"carburization": 5, "carbon": 4, "carburization process": 2, "gas circulation": 2, "part geometry": 0, "depth part geometry": 0, "case depth part": 0, "depth part": 0, "case depth": 0, "amount carbon": 0}}}, "Department of Agriculture": {"2017": {"agency": "Department of Agriculture", "year": "2017", "wd_ct": 278, "aw_ct": 1, "ids": ["2017-00470_2017-33610-26657"], "AGROVOC": {"pesticides": 9, "water": 8, "paper": 3, "monitoring": 3, "nanotechnology": 2, "equipment": 2, "food_safety": 1, "contamination": 1, "agriculture": 1, "safety": 1, "foods": 1, "health_hazards": 1, "time": 1, "site": 1, "pesticide_residues": 1, "calcium_ammonium_nitrate": 1, "data": 1, "carbamate_pesticides": 1}, "REEGLE": {"water_resources": 8, "monitoring": 3, "projects": 2, "agriculture": 1, "human_health": 1, "technical_feasibility": 1}, "GEMET": {"food": 7, "detection": 5, "paper": 3, "monitoring": 3, "safety": 2, "need": 2, "equipment": 2, "contamination": 1, "agriculture": 1, "human_health": 1, "time": 1, "line": 1, "screening": 1, "pesticide": 1, "fluidics": 1, "material": 1, "technology": 1, "calcium": 1, "ammonium": 1, "nitrate": 1, "resource": 1, "model": 1, "research": 1, "method": 1}, "EUSCIVOC": {"food_safety": 1, "agriculture": 1}, "EUVOC": {"chemical_salt": 2, "pollution": 1, "farming_sector": 1, "health_policy": 1, "literature": 1}, "STW": {"water": 8, "food": 7, "health_policy": 1, "customers": 1, "literature": 1, "technology": 1, "mobile_phone": 1, "data": 1}, "MeSH": {"Food_Safety": 1, "Pesticide_Residues": 1, "Wireless_Technology": 1}, "textrank": {"phase": 3, "paper": 3, "transfer": 1, "technology": 1, "detection pesticide food water": 0}, "tfidf_keywords": {"food": 8, "water": 8, "pesticide": 1, "food water": 0, "pesticide food water": 0, "pesticide food": 0, "detection pesticide": 0, "monitoring pesticide": 0, "monitoring pesticide food": 0, "paper system": 0}}}, "Department of Health and Human Services": {"2011": {"agency": "Department of Health and Human Services", "year": "2011", "wd_ct": 266, "aw_ct": 1, "ids": ["R43DK091143_1R43DK091143-01"], "AGROVOC": {"literacy": 5, "patients": 5, "nutrition_education": 3, "materials": 2, "dialysis": 2, "design": 2, "medical_sciences": 2, "public_health": 2, "prototypes": 1, "application": 1, "development": 1, "marketing": 1, "information": 1, "scientists": 1, "knowledge": 1, "population": 1}, "REEGLE": {"human_health": 4, "projects": 3, "international_development": 1, "partnerships": 1}, "GEMET": {"science": 5, "human_health": 4, "nutrition": 3, "education": 3, "research": 3, "minority": 2, "dialysis": 2, "software": 2, "product": 2, "approach": 2, "school": 2, "disease": 2, "public": 2, "marketing": 1, "information": 1, "business": 1}, "EUSCIVOC": {"kidney_disease": 2}, "EUVOC": {"health_policy": 4, "mass_media": 3, "designs_and_models": 2, "educational_institution": 2, "illness": 2, "scientific_press": 1}, "STW": {"science": 5, "illiteracy": 5, "patients": 5, "health_policy": 4, "education": 3, "minority": 2, "product": 2, "educational_institution": 2, "foundation": 1, "international": 1, "marketing": 1, "nature": 1, "population": 1, "labour": 1}, "MeSH": {"Health_Literacy": 2, "Kidney_Diseases": 2, "Public_Health": 2}, "textrank": {"health": 4, "treatment": 4, "science literacy": 3, "project": 3, "sbir": 3, "research": 3, "product": 2, "opportunity": 2, "carolina": 2, "patient": 0, "researcher": 0}, "tfidf_keywords": {"literacy": 5, "science literacy": 3, "nutrition education": 3, "university brody school": 2, "university brody": 2, "study treatment kidney": 0, "science literacy minority": 0, "purpose project nutrition": 0, "project nutrition education": 0, "nutrition education material": 0}}, "2013": {"agency": "Department of Health and Human Services", "year": "2013", "wd_ct": 403, "aw_ct": 1, "ids": ["R43ES023263_1R43ES023263-01"], "AGROVOC": {"pesticides": 8, "monitoring": 8, "blood": 4, "time": 3, "immunological_techniques": 2, "in_vitro": 2, "public_health": 2, "diagnosis": 1, "chemicals": 1, "health_hazards": 1, "assessment": 1, "risk": 1, "cholinesterase": 1, "fluorescence": 1, "nanoparticles": 1, "schools": 1, "workers": 1, "biomonitoring": 1, "development": 1, "results": 1, "portability": 1, "forecasting": 1, "calcium_ammonium_nitrate": 1}, "REEGLE": {"monitoring": 8, "human_health": 4, "research_programmes": 2, "chemicals_sector_processes": 1, "assessments": 1, "innovation": 1, "projects": 1, "technical_feasibility": 1, "international_development": 1}, "GEMET": {"monitoring": 8, "exposure": 8, "human_health": 4, "research": 3, "cost": 3, "detection": 3, "time": 3, "point": 2, "flow": 2, "test": 2, "public": 2, "insect": 1, "risk": 1, "business": 1, "innovation": 1, "biomarker": 1, "family": 1, "forecasting": 1, "calcium": 1, "ammonium": 1, "nitrate": 1, "epidemiology": 1}, "EUSCIVOC": {"diagnostic_technologies": 1}, "EUVOC": {"health_policy": 4, "chemical_salt": 2, "chemical_product": 1, "literature": 1, "metrology": 1}, "STW": {"health_policy": 4, "costs": 3, "control": 1, "product": 1, "innovation": 1, "students": 1, "international": 1, "literature": 1, "epidemic": 1}, "MeSH": {"Environmental_Monitoring": 8, "Environmental_Exposure": 5, "In_Vitro_Techniques": 2, "Public_Health": 2, "Insect_Control": 1, "Environmental_Health": 1, "Small_Business": 1, "Limit_of_Detection": 1, "Reaction_Time": 1, "Family": 1}, "textrank": {"device": 8, "exposure": 8, "health": 4, "detection": 3, "time": 3, "blood sample": 1, "pesticide": 0, "research project bio": 0, "nanoparticle flow": 0, "family member": 0}, "tfidf_keywords": {"op": 14, "bio monitoring": 8, "exposure": 8, "bio": 8, "monitoring": 8, "bio monitoring device": 5, "monitoring device": 5, "exposure op": 0, "pesticide": 0, "op pesticide": 0}}}, "National Aeronautics and Space Administration": {"2008": {"agency": "National Aeronautics and Space Administration", "year": "2008", "wd_ct": 198, "aw_ct": 1, "ids": ["65640_NNC08CA30C"], "AGROVOC": {"exploration": 3, "space": 2, "agencies": 1, "composition": 1, "solar_system": 1, "systems": 1, "energy_sources": 1, "analytes": 1, "spectroscopy": 1, "mass": 1, "development": 1, "investment": 1, "resources": 1}, "REEGLE": {"energy": 1, "tradable_permits": 1, "international_development": 1}, "GEMET": {"exploration": 3, "density": 2, "sensor": 2, "chemical": 2, "marker": 1, "energy": 1, "detection": 1, "science": 1, "instrumentation": 1, "spectroscopy": 1, "investment": 1}, "EUVOC": {"consultancy": 1}, "STW": {"measurement": 6, "energy": 1, "associates": 1, "science": 1, "future": 1, "international": 1}, "MeSH": {"Biological_Markers": 1, "Solar_System": 1, "Exobiology": 1, "Dielectric_Spectroscopy": 1}, "textrank": {"measurement": 6, "chemical": 2, "sensor array impedance analyzer exploration": 0, "mission nasa space": 0}, "tfidf_keywords": {"measurement": 6, "impedance": 5, "array": 4, "analyzer": 4, "array impedance": 2, "measurement channel": 2, "measurement channel density": 2, "array impedance analyzer": 2, "impedance analyzer": 2, "channel density": 2}}}}